{
  "switch_ip": "192.168.0.1",
  "switch_name": "SHOP",
  "switch_serial_number": "53H7235000000",
  "switch_bootloader": "unknown",
  "switch_firmware": "1.0.2.8",
  "port_1_status": "off",
  "port_1_modus_speed": true,
  "port_1_connection_speed": 0,
  "port_2_status": "off",
  "port_2_modus_speed": true,
  "port_2_connection_speed": 0,
  "port_3_status": "on",
  "port_3_modus_speed": true,
  "port_3_connection_speed": 100,
  "port_4_status": "on",
  "port_4_modus_speed": true,
  "port_4_connection_speed": 1000,
  "port_5_status": "on",
  "port_5_modus_speed": true,
  "port_5_connection_speed": 1000,
  "port_6_status": "off",
  "port_6_modus_speed": true,
  "port_6_connection_speed": 0,
  "port_7_status": "on",
  "port_7_modus_speed": true,
  "port_7_connection_speed": 100,
  "port_8_status": "on",
  "port_8_modus_speed": true,
  "port_8_connection_speed": 1000,
  "port_9_status": "on",
  "port_9_modus_speed": true,
  "port_9_connection_speed": 2500,
  "port_10_status": "on",
  "port_10_modus_speed": true,
  "port_10_connection_speed": 5000,
  "response_time_s": 0,
  "port_1_traffic_rx_mbytes": 0.0,
  "port_1_traffic_tx_mbytes": 0.0,
  "port_1_speed_rx_mbytes": 0.0,
  "port_1_speed_tx_mbytes": 0.0,
  "port_1_speed_io_mbytes": 0.0,
  "port_1_sum_rx_mbytes": 0.0,
  "port_1_sum_tx_mbytes": 0.0,
  "port_2_traffic_rx_mbytes": 0.0,
  "port_2_traffic_tx_mbytes": 0.0,
  "port_2_speed_rx_mbytes": 0.0,
  "port_2_speed_tx_mbytes": 0.0,
  "port_2_speed_io_mbytes": 0.0,
  "port_2_sum_rx_mbytes": 0.55,
  "port_2_sum_tx_mbytes": 299.52,
  "port_3_traffic_rx_mbytes": 0.0,
  "port_3_traffic_tx_mbytes": 0.0,
  "port_3_speed_rx_mbytes": 0.0,
  "port_3_speed_tx_mbytes": 0.0,
  "port_3_speed_io_mbytes": 0.0,
  "port_3_sum_rx_mbytes": 277.24,
  "port_3_sum_tx_mbytes": 7149.76,
  "port_4_traffic_rx_mbytes": 0.0,
  "port_4_traffic_tx_mbytes": 0.0,
  "port_4_speed_rx_mbytes": 0.0,
  "port_4_speed_tx_mbytes": 0.0,
  "port_4_speed_io_mbytes": 0.0,
  "port_4_sum_rx_mbytes": 17.48,
  "port_4_sum_tx_mbytes": 406.12,
  "port_5_traffic_rx_mbytes": 0.0,
  "port_5_traffic_tx_mbytes": 0.0,
  "port_5_speed_rx_mbytes": 0.0,
  "port_5_speed_tx_mbytes": 0.0,
  "port_5_speed_io_mbytes": 0.0,
  "port_5_sum_rx_mbytes": 0.0,
  "port_5_sum_tx_mbytes": 0.0,
  "port_6_traffic_rx_mbytes": 0.0,
  "port_6_traffic_tx_mbytes": 0.0,
  "port_6_speed_rx_mbytes": 0.0,
  "port_6_speed_tx_mbytes": 0.0,
  "port_6_speed_io_mbytes": 0.0,
  "port_6_sum_rx_mbytes": 4.77,
  "port_6_sum_tx_mbytes": 297.02,
  "port_7_traffic_rx_mbytes": 0.0,
  "port_7_traffic_tx_mbytes": 0.0,
  "port_7_speed_rx_mbytes": 0.0,
  "port_7_speed_tx_mbytes": 0.0,
  "port_7_speed_io_mbytes": 0.0,
  "port_7_sum_rx_mbytes": 1505.48,
  "port_7_sum_tx_mbytes": 998.65,
  "port_8_traffic_rx_mbytes": 0.0,
  "port_8_traffic_tx_mbytes": 0.0,
  "port_8_speed_rx_mbytes": 0.0,
  "port_8_speed_tx_mbytes": 0.0,
  "port_8_speed_io_mbytes": 0.0,
  "port_8_sum_rx_mbytes": 7535.48,
  "port_8_sum_tx_mbytes": 2596.7,
  "port_9_traffic_rx_mbytes": 0.0,
  "port_9_traffic_tx_mbytes": 0.0,
  "port_9_speed_rx_mbytes": 0.0,
  "port_9_speed_tx_mbytes": 0.0,
  "port_9_speed_io_mbytes": 0.0,
  "port_9_sum_rx_mbytes": 10236.22,
  "port_9_sum_tx_mbytes": 9347.28,
  "port_10_traffic_rx_mbytes": 0.0,
  "port_10_traffic_tx_mbytes": 0.0,
  "port_10_speed_rx_mbytes": 0.0,
  "port_10_speed_tx_mbytes": 0.0,
  "port_10_speed_io_mbytes": 0.0,
  "port_10_sum_rx_mbytes": 0.0,
  "port_10_sum_tx_mbytes": 0.0,
  "sum_port_traffic_rx": 0.0,
  "sum_port_traffic_tx": 0.0,
  "sum_port_speed_rx": 0.0,
  "sum_port_speed_tx": 0.0,
  "sum_port_speed_io": 0.0,
  "port_10_crc_errors": 0,
  "sum_port_crc_errors": 0
}
